LICENSE
README.md
pyproject.toml
setup.py
pyportfolioanalytics/__init__.py
pyportfolioanalytics/report.py
pyportfolioanalytics/utils.py
pyportfolioanalytics.egg-info/PKG-INFO
pyportfolioanalytics.egg-info/SOURCES.txt
pyportfolioanalytics.egg-info/dependency_links.txt
pyportfolioanalytics.egg-info/requires.txt
pyportfolioanalytics.egg-info/top_level.txt