Metadata-Version: 2.1
Name: pyportfolioanalytics
Version: 0.4.0
Summary: Librería para leer ficheros PDFs y extraer la información en formato str
Home-page: https://github.com/SebastianUrdaneguiBisalaya/py-portfolioanalytics
Author: Sebastian Marat Urdanegui Bisalaya
Author-email: sebasurdanegui@gmail.com
License: MIT
License-File: LICENSE
